sardine/__init__.py
sardine/actions/__init__.py
sardine/actions/base.py
sardine/actions/download_repositories.py
sardine/actions/execute_stack.py
sardine/actions/stop_stack.py
sardine/cli/__init__.py
sardine/cli/main.py
sardine/config.py
sardine/exceptions/__init__.py
sardine/exceptions/lang/__init__.py
sardine/exceptions/lang/lang_exception.py
sardine/exceptions/lang/manifest/__init__.py
sardine/exceptions/lang/manifest/cannot_redefine_alias.py
sardine/exceptions/lang/manifest/repository_alias_not_found.py
sardine/exceptions/lang/parser/__init__.py
sardine/exceptions/lang/parser/undefined_default_repository.py
sardine/exceptions/lang/parser/unexpected_token_found.py
sardine/exceptions/lang/tokenizer/__init__.py
sardine/exceptions/lang/tokenizer/unknown_token.py
sardine/exceptions/manifest_not_found.py
sardine/exceptions/sardine_exception.py
sardine/lang/__init__.py
sardine/lang/manifest/__init__.py
sardine/lang/manifest/builder.py
sardine/lang/mappings.py
sardine/lang/parser/__init__.py
sardine/lang/parser/objects.py
sardine/lang/parser/parser.py
sardine/lang/tokenizer/__init__.py
sardine/lang/tokenizer/objects.py
sardine/lang/tokenizer/tokenizer.py
sardine/lang/tokenizer/tokens.py
sardine/resolvers/__init__.py
sardine/resolvers/manifest/__init__.py
sardine/resolvers/manifest/base.py
sardine/resolvers/manifest/local.py
sardine/resolvers/repository/__init__.py
sardine/resolvers/repository/base.py
sardine/resolvers/repository/remote.py
sardine/types.py
sardine-0.0.0b3.dist-info/entry_points.txt
sardine-0.0.0b3.dist-info/LICENSE
sardine-0.0.0b3.dist-info/WHEEL
sardine-0.0.0b3.dist-info/METADATA
sardine-0.0.0b3.dist-info/RECORD
